canvass.py
canvass-0.1.dist-info/DESCRIPTION.rst
canvass-0.1.dist-info/METADATA
canvass-0.1.dist-info/RECORD
canvass-0.1.dist-info/WHEEL
canvass-0.1.dist-info/dependency_links.txt
canvass-0.1.dist-info/metadata.json
canvass-0.1.dist-info/top_level.txt
