Metadata-Version: 2.0
Name: canvass
Version: 0.1
Summary: Ask a tree-based series of questions, using inquirer
Home-page: https://github.com/djf604/canvass
Author: Dominic Fitzgerald
Author-email: dominicfitzgerald11@gmail.com
License: MIT
Platform: UNKNOWN
Classifier: Development Status :: 4 - Beta
Classifier: Environment :: Console
Classifier: License :: OSI Approved :: MIT License
Classifier: Programming Language :: Python
Classifier: Topic :: Software Development :: Libraries
Classifier: Topic :: Utilities
Requires-Dist: inquirer
